pyuvvm/__init__.py
pyuvvm-0.0.1.dist-info/LICENSE
pyuvvm-0.0.1.dist-info/METADATA
pyuvvm-0.0.1.dist-info/WHEEL
pyuvvm-0.0.1.dist-info/top_level.txt
pyuvvm-0.0.1.dist-info/RECORD
